Workbook

Sheet 汇总
A1: 汇总与折算（公式驱动，唯一维护处）
A3: WBS | B3: 模块/阶段 | C3: 人日小计 | D3: 开始日期 | E3: 结束日期 | F3: 关键风险/依赖
A4: A1 | B4: 需求调研与PRD | C4: =SUMIF('功能点评估（全栈）'!$A$4:$A$69,$A4,'功能点评估（全栈）'!$G$4:$G$69) -> 0 | D4: =IF(COUNT('功能点评估（全栈）'!I4:I7)=0,"",MIN('功能点评估（全栈）'!I4:I7)) | E4: =IF(COUNT('功能点评估（全栈）'!J4:J7)=0,"",MAX('功能点评估（全栈）'!J4:J7)) | F4: #2 #3 材料未齐即启动，PRD 有返工风险
A5: A2 | B5: 原型设计 | C5: =SUMIF('功能点评估（全栈）'!$A$4:$A$69,$A5,'功能点评估（全栈）'!$G$4:$G$69) -> 0 | D5: =IF(COUNT('功能点评估（全栈）'!I8:I9)=0,"",MIN('功能点评估（全栈）'!I8:I9)) | E5: =IF(COUNT('功能点评估（全栈）'!J8:J9)=0,"",MAX('功能点评估（全栈）'!J8:J9)) | F5: v2.8 已交付，仅评修订量
A6: B0 | B6: 公共技术底座 | C6: =SUMIF('功能点评估（全栈）'!$A$4:$A$69,$A6,'功能点评估（全栈）'!$G$4:$G$69) -> 0 | D6: =IF(COUNT('功能点评估（全栈）'!I10:I12)=0,"",MIN('功能点评估（全栈）'!I10:I12)) | E6: =IF(COUNT('功能点评估（全栈）'!J10:J12)=0,"",MAX('功能点评估（全栈）'!J10:J12))
A7: B1 | B7: 基础数据 | C7: =SUMIF('功能点评估（全栈）'!$A$4:$A$69,$A7,'功能点评估（全栈）'!$G$4:$G$69) -> 0 | D7: =IF(COUNT('功能点评估（全栈）'!I13:I18)=0,"",MIN('功能点评估（全栈）'!I13:I18)) | E7: =IF(COUNT('功能点评估（全栈）'!J13:J18)=0,"",MAX('功能点评估（全栈）'!J13:J18))
A8: B2 | B8: 项目管理中心 | C8: =SUMIF('功能点评估（全栈）'!$A$4:$A$69,$A8,'功能点评估（全栈）'!$G$4:$G$69) -> 0 | D8: =IF(COUNT('功能点评估（全栈）'!I19:I23)=0,"",MIN('功能点评估（全栈）'!I19:I23)) | E8: =IF(COUNT('功能点评估（全栈）'!J19:J23)=0,"",MAX('功能点评估（全栈）'!J19:J23))
A9: B3 | B9: 仓储作业 ★核心 | C9: =SUMIF('功能点评估（全栈）'!$A$4:$A$69,$A9,'功能点评估（全栈）'!$G$4:$G$69) -> 0 | D9: =IF(COUNT('功能点评估（全栈）'!I24:I36)=0,"",MIN('功能点评估（全栈）'!I24:I36)) | E9: =IF(COUNT('功能点评估（全栈）'!J24:J36)=0,"",MAX('功能点评估（全栈）'!J24:J36)) | F9: 13 类单据；组装/拆卸为全新逻辑，PRD 冻结前估算偏差大
A10: B4 | B10: 包装管理（租赁） | C10: =SUMIF('功能点评估（全栈）'!$A$4:$A$69,$A10,'功能点评估（全栈）'!$G$4:$G$69) -> 0 | D10: =IF(COUNT('功能点评估（全栈）'!I37:I42)=0,"",MIN('功能点评估（全栈）'!I37:I42)) | E10: =IF(COUNT('功能点评估（全栈）'!J37:J42)=0,"",MAX('功能点评估（全栈）'!J37:J42)) | F10: #1 计费规则未确认（US-14 暂不在基线）
A11: B5 | B11: 订单管理 | C11: =SUMIF('功能点评估（全栈）'!$A$4:$A$69,$A11,'功能点评估（全栈）'!$G$4:$G$69) -> 0 | D11: =IF(COUNT('功能点评估（全栈）'!I43:I46)=0,"",MIN('功能点评估（全栈）'!I43:I46)) | E11: =IF(COUNT('功能点评估（全栈）'!J43:J46)=0,"",MAX('功能点评估（全栈）'!J43:J46)) | F11: #6 路凯对接方式待定
A12: B6 | B12: 财务协同 | C12: =SUMIF('功能点评估（全栈）'!$A$4:$A$69,$A12,'功能点评估（全栈）'!$G$4:$G$69) -> 0 | D12: =IF(COUNT('功能点评估（全栈）'!I47:I53)=0,"",MIN('功能点评估（全栈）'!I47:I53)) | E12: =IF(COUNT('功能点评估（全栈）'!J47:J53)=0,"",MAX('功能点评估（全栈）'!J47:J53)) | F12: #5 单据/水单样例、#8 开票主体待提供
A13: B7 | B13: 系统管理 | C13: =SUMIF('功能点评估（全栈）'!$A$4:$A$69,$A13,'功能点评估（全栈）'!$G$4:$G$69) -> 0 | D13: =IF(COUNT('功能点评估（全栈）'!I54:I56)=0,"",MIN('功能点评估（全栈）'!I54:I56)) | E13: =IF(COUNT('功能点评估（全栈）'!J54:J56)=0,"",MAX('功能点评估（全栈）'!J54:J56))
A14: B8 | B14: 采购管理 | C14: =SUMIF('功能点评估（全栈）'!$A$4:$A$69,$A14,'功能点评估（全栈）'!$G$4:$G$69) -> 0 | D14: =IF(COUNT('功能点评估（全栈）'!I57:I61)=0,"",MIN('功能点评估（全栈）'!I57:I61)) | E14: =IF(COUNT('功能点评估（全栈）'!J57:J61)=0,"",MAX('功能点评估（全栈）'!J57:J61)) | F14: 第 2 次会新增模块（09-04 拍板第一期闭环）
A15: C1 | B15: 测试 | C15: =SUMIF('功能点评估（全栈）'!$A$4:$A$69,$A15,'功能点评估（全栈）'!$G$4:$G$69) -> 0 | D15: =IF(COUNT('功能点评估（全栈）'!I62:I63)=0,"",MIN('功能点评估（全栈）'!I62:I63)) | E15: =IF(COUNT('功能点评估（全栈）'!J62:J63)=0,"",MAX('功能点评估（全栈）'!J62:J63)) | F15: 用例需覆盖 F01 五条主线全链路
A16: C2 | B16: 数据迁移 | C16: =SUMIF('功能点评估（全栈）'!$A$4:$A$69,$A16,'功能点评估（全栈）'!$G$4:$G$69) -> 0 | D16: =IF(COUNT('功能点评估（全栈）'!I64:I66)=0,"",MIN('功能点评估（全栈）'!I64:I66)) | E16: =IF(COUNT('功能点评估（全栈）'!J64:J66)=0,"",MAX('功能点评估（全栈）'!J64:J66)) | F16: #4 主数据清单与格式待提供
A17: C3 | B17: 上线部署 | C17: =SUMIF('功能点评估（全栈）'!$A$4:$A$69,$A17,'功能点评估（全栈）'!$G$4:$G$69) -> 0 | D17: =IF(COUNT('功能点评估（全栈）'!I67:I69)=0,"",MIN('功能点评估（全栈）'!I67:I69)) | E17: =IF(COUNT('功能点评估（全栈）'!J67:J69)=0,"",MAX('功能点评估（全栈）'!J67:J69)) | F17: 试运行窗口待与客户确认
B18: 合计 / 全跨度 | C18: =SUM(C4:C17) -> 0 | D18: =IF(COUNT(D4:D17)=0,"",MIN(D4:D17)) | E18: =IF(COUNT(E4:E17)=0,"",MAX(E4:E17))
A20: 参数与折算
A21: 缓冲比例 | D21: 黄格待填：建议 15%~20%，覆盖联调与管理裕度
A22: 投入人数 | D22: 黄格待填：对应 P1-R01 第八节 #9
A23: 每月工作日 | C23: 21 | D23: 人月折算基准
A24: 含缓冲合计（人日） | C24: =IF(OR($C$21="",$C$18=0),"",$C$18*(1+$C$21)) | D24: 自动：合计×(1+缓冲)
A25: 日历工期（月） | C25: =IF(OR($C$21="",$C$22="",$C$22=0,$C$24=""),"",$C$24/($C$23*$C$22)) | D25: 自动：含缓冲÷(每月工作日×人数)
A26: 日历工期（周） | C26: =IF(OR($C$21="",$C$22="",$C$22=0,$C$24=""),"",$C$24/($C$23*$C$22)*4.33) | D26: 自动

Sheet 功能点评估（全栈）
A1: P1-R03 工期评估表 · 功能点级（全栈口径）
A2: 口径：人日含概要设计+编码+自测；每功能点一行、不分前后端（类型=全栈）。本表 2026-09-05 按 P1-R01 §5.1（39 FP）+ 原型 v2.8（45 页/79 弹窗）+ F01 v2.8 重制：任务行挂「对应原型页面」列；标（待补）的 10 行为原型已有但 §5.1 未编 FP 码的页面，评估按页面实际范围、编码后续补。人日/评估人/开始/结束全部留白，由道远与开发逐行填写；上一版估算与排期已归档于 99-归档/P1-R03-工期评估表-20260905.xlsx。
A3: WBS | B3: 模块/阶段 | C3: 功能点 | D3: 任务 | E3: 类型 | F3: 对应原型页面 | G3: 人日 | H3: 评估人 | I3: 开始时间 | J3: 结束时间 | K3: 备注（风险/依赖）
A4: A1 | B4: 需求调研与PRD | C4: — | D4: 原型页面走查与字段确认（45 页逐页过、与吉客云/路凯现状对照） | E4: 调研 | F4: 45 页全量 | K4: 依赖 #2 #3：账号或全套截图；走查结论直接落到 PRD
A5: A1 | B5: 需求调研与PRD | C5: — | D5: 计费规则与单据流程确认（含四态计费口径） | E5: 调研 | F5: — | K5: 依赖 #1 #5：合同/报价单、单据样例
A6: A1 | B6: 需求调研与PRD | C6: — | D6: PRD 编写（按模块分册，以原型页面为底稿） | E6: 文档 | F6: 45 页全量
A7: A1 | B7: 需求调研与PRD | C7: — | D7: PRD 评审与范围冻结 | E7: 文档 | F7: 45 页全量 | K7: 客户确认后冻结范围，原型同步定稿
A8: A2 | B8: 原型设计 | C8: — | D8: 原型按评审反馈修订 | E8: 原型 | F8: 涉及页视反馈 | K8: v2.8 已交付（45 页 + 79 弹窗 + F01 导航图），仅评修订量，勿按全量重估
A9: A2 | B9: 原型设计 | C9: — | D9: 原型评审确认与定稿 | E9: 原型 | F9: 45 页全量 + F01 | K9: 与 PRD 冻结同节点收口
A10: B0 | B10: 公共技术底座 | C10: — | D10: 工程脚手架与 CI/CD | E10: 全栈 | F10: — | K10: 本表新增项，非 P1-R01 功能点，评估时确认保留
A11: B0 | B11: 公共技术底座 | C11: — | D11: 登录认证与框架权限 | E11: 全栈 | F11: — | K11: 原型未含登录页，按通用方案实现
A12: B0 | B12: 公共技术底座 | C12: — | D12: 通用组件（单据/列表/导入导出/弹窗/四段式详情） | E12: 全栈 | F12: 全站 | K12: 复刻原型交互；79 个弹窗模板与四段式详情组件可直接参照
A13: B1 | B13: 基础数据 | C13: FP1-01 | D13: 项目档案：页面 + 表结构与接口 | E13: 全栈 | F13: 项目档案
A14: B1 | B14: 基础数据 | C14: FP1-02 | D14: 客商管理：三类客商档案（含开票资料） | E14: 全栈 | F14: 客商管理
A15: B1 | B15: 基础数据 | C15: FP1-03 | D15: 器具档案：页面 + 接口 | E15: 全栈 | F15: 器具档案
A16: B1 | B16: 基础数据 | C16: FP1-04 | D16: 零部件档案：页面 + 接口 | E16: 全栈 | F16: 零部件档案
A17: B1 | B17: 基础数据 | C17: FP1-05 | D17: 子母件 BOM：维护页 + 版本管理与配比校验 | E17: 全栈 | F17: BOM + BOM维护（2页） | K17: 配比错误需拦截
A18: B1 | B18: 基础数据 | C18: FP1-06 | D18: 库位档案：页面 + 接口（仓/区/位三级） | E18: 全栈 | F18: 库位档案 | K18: 预留扫码接口（REQ-20）
A19: B2 | B19: 项目管理中心 | C19: FP2-01 | D19: 项目编码规则：规则引擎 + 配置 | E19: 全栈 | F19: 项目档案（编码规则弹窗）
A20: B2 | B20: 项目管理中心 | C20: FP2-02 | D20: 上下游绑定：关系维护 + 模型接口 | E20: 全栈 | F20: 项目档案（上下游绑定弹窗）
A21: B2 | B21: 项目管理中心 | C21: FP2-03 | D21: 项目看板：图表页 + 统计接口 | E21: 全栈 | F21: 首页·项目看板
A22: B2 | B22: 项目管理中心 | C22: FP2-04 | D22: 明细查看：从汇总数据进入单据明细 | E22: 全栈 | F22: 项目详情
A23: B2 | B23: 项目管理中心 | C23: （待补） | D23: 我的待办：18 类待办聚合入口 | E23: 全栈 | F23: 首页·我的待办 | K23: FP 码待补（§5.1 未编）；聚合各模块待办，需各模块联动
A24: B3 | B24: 仓储作业 ★核心 | C24: FP3-01 | D24: 采购入库单（执行）：录单 + 入库过账与库存更新 | E24: 全栈 | F24: 采购入库 列表+录单（2页） | K24: 由 FP8-03 到货发起，凭单验收
A25: B3 | B25: 仓储作业 ★核心 | C25: FP3-02 ★新增 | D25: 组装单：录单 + 库存转换引擎（A+B→C） | E25: 全栈 | F25: 组装 列表+录单（2页） | K25: 新逻辑：组装动作首次入系统；组装后散件转成品库存
A26: B3 | B26: 仓储作业 ★核心 | C26: FP3-03 | D26: 组合出库单：录单 + 出库过账与台账联动 | E26: 全栈 | F26: 组合出库 列表+录单（2页）
A27: B3 | B27: 仓储作业 ★核心 | C27: FP3-04 | D27: 退租入库验收单：按零件核对缺损并记明细 | E27: 全栈 | F27: 退租入库列表（审核弹窗） | K27: 由退租申请（B4）触发；退租入库加拆散去向（v2.8）
A28: B3 | B28: 仓储作业 ★核心 | C28: FP3-05 | D28: 盘点单：零件/组合双口径 + 盘盈亏过账 | E28: 全栈 | F28: 盘点 列表+录入（2页）
A29: B3 | B29: 仓储作业 ★核心 | C29: FP3-06 | D29: 库存查询：零件/组合双视角 + 库存流水 | E29: 全栈 | F29: 库存查询（含流水弹窗）
A30: B3 | B30: 仓储作业 ★核心 | C30: （待补） | D30: 销售出库单：录单 + 出库过账（买卖线出库执行） | E30: 全栈 | F30: 销售出库列表（新建/审核弹窗） | K30: FP 码待补；FP8-04 销售订单审核后走此单出库
A31: B3 | B31: 仓储作业 ★核心 | C31: （待补） | D31: 其他入库单：无单据来源杂项入库 | E31: 全栈 | F31: 其他入库列表（新建/审核弹窗） | K31: FP 码待补
A32: B3 | B32: 仓储作业 ★核心 | C32: （待补） | D32: 其他出库单：报废/杂项出库 | E32: 全栈 | F32: 其他出库列表（新建/审核弹窗） | K32: FP 码待补
A33: B3 | B33: 仓储作业 ★核心 | C33: （待补） | D33: 库存调拨单：库间调拨 + 过账 | E33: 全栈 | F33: 库存调拨列表（新建/审核弹窗） | K33: FP 码待补
A34: B3 | B34: 仓储作业 ★核心 | C34: （待补） | D34: 拆卸单：C→A+B 逆向、散件回库 | E34: 全栈 | F34: 拆卸管理列表（新建/审核弹窗） | K34: FP 码待补；组装逆向，应对日计划变更
A35: B3 | B35: 仓储作业 ★核心 | C35: （待补） | D35: 租入入库单：租入包装验收入库（L3/L4） | E35: 全栈 | F35: 租入入库列表（确认弹窗） | K35: FP 码待补；租入体系独立单据（09-04 拍板）
A36: B3 | B36: 仓储作业 ★核心 | C36: （待补） | D36: 租入归还单：归还供应商出库（L3/L4） | E36: 全栈 | F36: 租入归还列表（新建/审核弹窗） | K36: FP 码待补
A37: B4 | B37: 包装管理（租赁） | C37: FP4-01 | D37: 租出台账：页面 + 接口 | E37: 全栈 | F37: 租出台账 | K37: 资产来源标记（v2.8）
A38: B4 | B38: 包装管理（租赁） | C38: FP4-02 | D38: 在租台账：在库/在途/客户端/退租四态统计 | E38: 全栈 | F38: 在租台账（器具出租履历弹窗）
A39: B4 | B39: 包装管理（租赁） | C39: FP4-03 | D39: 循环状态与计费：状态流转 + 按数量结算 | E39: 全栈 | F39: 在租台账（状态操作） | K39: #1 计费规则未确认；租金自动计费（US-14）暂不在基线
A40: B4 | B40: 包装管理（租赁） | C40: FP4-04 | D40: 丢损赔偿单：退租缺损自动生成赔偿应收 | E40: 全栈 | F40: 丢损赔偿单（审核/报废弹窗）
A41: B4 | B41: 包装管理（租赁） | C41: FP4-05 | D41: 租赁单（出租）：向客户租出、生成租赁单 | E41: 全栈 | F41: 租赁单列表（新建/审核弹窗） | K41: 替代原「客户下单」，关联项目与客户
A42: B4 | B42: 包装管理（租赁） | C42: （待补） | D42: 退租申请：客户退租入口，触发验收 | E42: 全栈 | F42: 退租申请列表（新建/审核弹窗） | K42: FP 码待补；L4 退租申请节点（v2.8）
A43: B5 | B43: 订单管理 | C43: FP5-01 | D43: 订单管理（代下单）：项目经理代客户下单、统一订单列表 | E43: 全栈 | F43: 销售订单列表（租赁/买卖两用） | K43: REQ-07：客户发 PO、不再分客户端
A44: B5 | B44: 订单管理 | C44: FP5-02 | D44: 订单审核：工作台 + 审核流转 | E44: 全栈 | F44: 销售订单审核弹窗
A45: B5 | B45: 订单管理 | C45: FP5-03 | D45: 订单同步（路凯）：同步通道 + 记录重发 | E45: 全栈 | F45: 后台通道（无独立页） | K45: #6 对接方式待定，评估按导出/接口两档
A46: B5 | B46: 订单管理 | C46: FP5-04 | D46: 结算数据导出：数据生成 + 传递 | E46: 全栈 | F46: 后台逻辑 + 导出入口 | K46: #6 结算格式待路凯方提供
A47: B6 | B47: 财务协同 | C47: FP6-01 | D47: 应收账单生成：归集规则 + 账单页 | E47: 全栈 | F47: 应收账单（生成/详情弹窗）
A48: B6 | B48: 财务协同 | C48: FP6-02 | D48: 开票登记与发票上传：登记 + 应收关联 | E48: 全栈 | F48: 开票登记（新建/详情弹窗） | K48: 依赖 #8 开票主体信息
A49: B6 | B49: 财务协同 | C49: FP6-03 | D49: 回款登记：到账录入 + 关联 | E49: 全栈 | F49: 回款登记（收款登记弹窗）
A50: B6 | B50: 财务协同 | C50: FP6-04 ★补缺 | D50: 银行水单核销：导入勾对 + 部分核销 + 对账联调 | E50: 全栈 | F50: 银行水单核销（勾对工作台） | K50: 现状缺失环节；依赖 #5 水单样例
A51: B6 | B51: 财务协同 | C51: FP6-05 | D51: 项目盈亏报表：汇总计算 + 报表页 | E51: 全栈 | F51: 盈亏报表
A52: B6 | B52: 财务协同 | C52: FP6-06 ★新增 | D52: 应付账单：采购/租入自动生成应付（第一期简化） | E52: 全栈 | F52: 应付账单（新建/详情弹窗） | K52: REQ-21；租金应付可跳租入单（v2.8）
A53: B6 | B53: 财务协同 | C53: FP6-07 ★新增 | D53: 付款登记：银行付款录入，关联应付 | E53: 全栈 | F53: 付款登记（新建/付款确认弹窗） | K53: REQ-21
A54: B7 | B54: 系统管理 | C54: FP7-01 | D54: 组织与权限：用户/角色/数据权限（我方/客户区分） | E54: 全栈 | F54: 用户权限（角色管理弹窗）
A55: B7 | B55: 系统管理 | C55: FP7-02 | D55: 操作日志：埋点存储 + 查询页 | E55: 全栈 | F55: 操作日志
A56: B7 | B56: 系统管理 | C56: FP7-03 | D56: 数据字典：字典管理 + 配置页 | E56: 全栈 | F56: 数据字典（新增字典项弹窗）
A57: B8 | B57: 采购管理 | C57: FP8-01 | D57: 采购订单：新建 + 列表（先销后采/先采后销） | E57: 全栈 | F57: 采购订单列表（新建/详情弹窗） | K57: B1 采购线（09-04 拍板，不以销定采）
A58: B8 | B58: 采购管理 | C58: FP8-02 | D58: 采购订单审核：状态流（待提交/待审核/已完成） | E58: 全栈 | F58: 采购订单审核弹窗
A59: B8 | B59: 采购管理 | C59: FP8-03 | D59: 采购入库（发起）：到货登记关联采购订单 | E59: 全栈 | F59: 采购入库列表（凭单验收注记） | K59: 执行由 FP3-01 承接
A60: B8 | B60: 采购管理 | C60: FP8-04 | D60: 销售订单（买卖线）：客户购买订单 | E60: 全栈 | F60: 销售订单列表（与 FP5-01 同页两线） | K60: 审核后走销售出库（B3）
A61: B8 | B61: 采购管理 | C61: （待补） | D61: 租入单：向路凯/供应商租入包装（L3/L4） | E61: 全栈 | F61: 租入单列表（新建/审核弹窗） | K61: FP 码待补；租入体系起点，触发租入入库
A62: C1 | B62: 测试 | C62: — | D62: 集成测试用例编写与执行 | E62: 测试 | F62: F01 导航图 v2.8 | K62: 覆盖 F01 五条主线（B1 销售/采购双线、L1~L4）+ S1~S7 支线 + 应收/应付财务通道
A63: C1 | B63: 测试 | C63: — | D63: UAT 支持与缺陷修复 | E63: 测试 | F63: —
A64: C2 | B64: 数据迁移 | C64: — | D64: 主数据整理与导入模板 | E64: 迁移 | F64: — | K64: 依赖 #4 主数据清单
A65: C2 | B65: 数据迁移 | C65: — | D65: 期初库存与在租数据迁移（含租入在途） | E65: 迁移 | F65: — | K65: 依赖 #5 现有台账导出
A66: C2 | B66: 数据迁移 | C66: — | D66: 迁移核对与差异处理 | E66: 迁移 | F66: —
A67: C3 | B67: 上线部署 | C67: — | D67: 环境部署与发布 | E67: 部署 | F67: —
A68: C3 | B68: 上线部署 | C68: — | D68: 上线切换与并行期支持 | E68: 部署 | F68: —
A69: C3 | B69: 上线部署 | C69: — | D69: 线上试运行与并行验证（真实订单并行跑、问题快速响应） | E69: 测试 | F69: — | K69: 建议预留 2~4 周试运行窗口，客户验收后转正式运行
D70: 合计（人日） | G70: =SUM(G4:G69) -> 0
