Workbook

Sheet 汇总
A1: 汇总与折算（公式驱动，唯一维护处）
A3: WBS | B3: 模块/阶段 | C3: 人日小计 | D3: 开始日期 | E3: 结束日期 | F3: 关键风险/依赖
A4: A1 | B4: 需求调研与PRD | C4: =SUMIF('功能点评估（全栈）'!$A$4:$A$69,$A4,'功能点评估（全栈）'!$H$4:$H$69) -> 6 | D4: =IF(COUNT('功能点评估（全栈）'!K4:K7)=0,"",MIN('功能点评估（全栈）'!K4:K7)) -> 46272 | E4: =IF(COUNT('功能点评估（全栈）'!L4:L7)=0,"",MAX('功能点评估（全栈）'!L4:L7)) -> 46276 | F4: #2 #3 材料未齐即启动，PRD 有返工风险
A5: A2 | B5: 原型设计 | C5: =SUMIF('功能点评估（全栈）'!$A$4:$A$69,$A5,'功能点评估（全栈）'!$H$4:$H$69) -> 1 | D5: =IF(COUNT('功能点评估（全栈）'!K8:K9)=0,"",MIN('功能点评估（全栈）'!K8:K9)) -> 46275 | E5: =IF(COUNT('功能点评估（全栈）'!L8:L9)=0,"",MAX('功能点评估（全栈）'!L8:L9)) -> 46276 | F5: v2.8 已交付，仅评修订量
A6: B0 | B6: 公共技术底座 | C6: =SUMIF('功能点评估（全栈）'!$A$4:$A$69,$A6,'功能点评估（全栈）'!$H$4:$H$69) -> 5.5 | D6: =IF(COUNT('功能点评估（全栈）'!K10:K12)=0,"",MIN('功能点评估（全栈）'!K10:K12)) -> 46272 | E6: =IF(COUNT('功能点评估（全栈）'!L10:L12)=0,"",MAX('功能点评估（全栈）'!L10:L12)) -> 46275
A7: B1 | B7: 基础数据 | C7: =SUMIF('功能点评估（全栈）'!$A$4:$A$69,$A7,'功能点评估（全栈）'!$H$4:$H$69) -> 9.5 | D7: =IF(COUNT('功能点评估（全栈）'!K13:K18)=0,"",MIN('功能点评估（全栈）'!K13:K18)) -> 46275 | E7: =IF(COUNT('功能点评估（全栈）'!L13:L18)=0,"",MAX('功能点评估（全栈）'!L13:L18)) -> 46316
A8: B2 | B8: 项目管理中心 | C8: =SUMIF('功能点评估（全栈）'!$A$4:$A$69,$A8,'功能点评估（全栈）'!$H$4:$H$69) -> 6.5 | D8: =IF(COUNT('功能点评估（全栈）'!K19:K23)=0,"",MIN('功能点评估（全栈）'!K19:K23)) -> 46275 | E8: =IF(COUNT('功能点评估（全栈）'!L19:L23)=0,"",MAX('功能点评估（全栈）'!L19:L23)) -> 46308
A9: B3 | B9: 仓储作业 ★核心 | C9: =SUMIF('功能点评估（全栈）'!$A$4:$A$69,$A9,'功能点评估（全栈）'!$H$4:$H$69) -> 27.5 | D9: =IF(COUNT('功能点评估（全栈）'!K24:K36)=0,"",MIN('功能点评估（全栈）'!K24:K36)) -> 46276 | E9: =IF(COUNT('功能点评估（全栈）'!L24:L36)=0,"",MAX('功能点评估（全栈）'!L24:L36)) -> 46342 | F9: 13 类单据；组装/拆卸为全新逻辑，PRD 冻结前估算偏差大
A10: B4 | B10: 包装管理（租赁） | C10: =SUMIF('功能点评估（全栈）'!$A$4:$A$69,$A10,'功能点评估（全栈）'!$H$4:$H$69) -> 13.5 | D10: =IF(COUNT('功能点评估（全栈）'!K37:K42)=0,"",MIN('功能点评估（全栈）'!K37:K42)) -> 46307 | E10: =IF(COUNT('功能点评估（全栈）'!L37:L42)=0,"",MAX('功能点评估（全栈）'!L37:L42)) -> 46331 | F10: #1 计费规则未确认（US-14 暂不在基线）
A11: B5 | B11: 订单管理 | C11: =SUMIF('功能点评估（全栈）'!$A$4:$A$69,$A11,'功能点评估（全栈）'!$H$4:$H$69) -> 9 | D11: =IF(COUNT('功能点评估（全栈）'!K43:K46)=0,"",MIN('功能点评估（全栈）'!K43:K46)) -> 46276 | E11: =IF(COUNT('功能点评估（全栈）'!L43:L46)=0,"",MAX('功能点评估（全栈）'!L43:L46)) -> 46343 | F11: #6 路凯对接方式待定
A12: B6 | B12: 财务协同 | C12: =SUMIF('功能点评估（全栈）'!$A$4:$A$69,$A12,'功能点评估（全栈）'!$H$4:$H$69) -> 15.5 | D12: =IF(COUNT('功能点评估（全栈）'!K47:K53)=0,"",MIN('功能点评估（全栈）'!K47:K53)) -> 46282 | E12: =IF(COUNT('功能点评估（全栈）'!L47:L53)=0,"",MAX('功能点评估（全栈）'!L47:L53)) -> 46349 | F12: #5 单据/水单样例、#8 开票主体待提供
A13: B7 | B13: 系统管理 | C13: =SUMIF('功能点评估（全栈）'!$A$4:$A$69,$A13,'功能点评估（全栈）'!$H$4:$H$69) -> 2 | D13: =IF(COUNT('功能点评估（全栈）'!K54:K56)=0,"",MIN('功能点评估（全栈）'!K54:K56)) -> 46289 | E13: =IF(COUNT('功能点评估（全栈）'!L54:L56)=0,"",MAX('功能点评估（全栈）'!L54:L56)) -> 46342
A14: B8 | B14: 采购管理 | C14: =SUMIF('功能点评估（全栈）'!$A$4:$A$69,$A14,'功能点评估（全栈）'!$H$4:$H$69) -> 8 | D14: =IF(COUNT('功能点评估（全栈）'!K57:K61)=0,"",MIN('功能点评估（全栈）'!K57:K61)) -> 46286 | E14: =IF(COUNT('功能点评估（全栈）'!L57:L61)=0,"",MAX('功能点评估（全栈）'!L57:L61)) -> 46336 | F14: 第 2 次会新增模块（09-04 拍板第一期闭环）
A15: C1 | B15: 测试 | C15: =SUMIF('功能点评估（全栈）'!$A$4:$A$69,$A15,'功能点评估（全栈）'!$H$4:$H$69) -> 17 | D15: =IF(COUNT('功能点评估（全栈）'!K62:K63)=0,"",MIN('功能点评估（全栈）'!K62:K63)) -> 46303 | E15: =IF(COUNT('功能点评估（全栈）'!L62:L63)=0,"",MAX('功能点评估（全栈）'!L62:L63)) -> 46360 | F15: 用例需覆盖 F01 五条主线全链路
A16: C2 | B16: 数据迁移 | C16: =SUMIF('功能点评估（全栈）'!$A$4:$A$69,$A16,'功能点评估（全栈）'!$H$4:$H$69) -> 13 | D16: =IF(COUNT('功能点评估（全栈）'!K64:K66)=0,"",MIN('功能点评估（全栈）'!K64:K66)) -> 46303 | E16: =IF(COUNT('功能点评估（全栈）'!L64:L66)=0,"",MAX('功能点评估（全栈）'!L64:L66)) -> 46360 | F16: #4 主数据清单与格式待提供
A17: C3 | B17: 上线部署 | C17: =SUMIF('功能点评估（全栈）'!$A$4:$A$69,$A17,'功能点评估（全栈）'!$H$4:$H$69) -> 15 | D17: =IF(COUNT('功能点评估（全栈）'!K67:K69)=0,"",MIN('功能点评估（全栈）'!K67:K69)) -> 46308 | E17: =IF(COUNT('功能点评估（全栈）'!L67:L69)=0,"",MAX('功能点评估（全栈）'!L67:L69)) -> 46374 | F17: 试运行窗口待与客户确认
B18: 合计 / 全跨度 | C18: =SUM(C4:C17) -> 149 | D18: =IF(COUNT(D4:D17)=0,"",MIN(D4:D17)) -> 46272 | E18: =IF(COUNT(E4:E17)=0,"",MAX(E4:E17)) -> 46374
A20: 版本划分小计（方案二·买卖先行，2026-09-05 拍板）
A21: 版本 | B21: 范围说明 | C21: 人日小计 | D21: 开始日期 | E21: 结束日期
A22: 前置 | B22: 调研/PRD/原型修订/技术底座（A1+A2+B0，9 行）——首版开工前提 | C22: =SUMIF('功能点评估（全栈）'!$G$4:$G$69,$A22,'功能点评估（全栈）'!$H$4:$H$69) -> 12.5 | D22: 2026-09-07 | E22: 2026-09-11
A23: V1.0 | B23: 买卖版 · 17 页上线（盘点/看板/项目详情 3 项移 V1.1）：买卖全链（采购订单→入库→销售订单→销售出库）+ 库存（查询/调拨/其他出入库）+ 应收/收款 + 权限；零新逻辑，出活最快；2026-10-16 上线 | C23: =SUMIF('功能点评估（全栈）'!$G$4:$G$69,$A23,'功能点评估（全栈）'!$H$4:$H$69) -> 32.5 | D23: 2026-09-10 | E23: 2026-10-16
A24: V1.1 | B24: 租赁版 · +20 页（含 V1.0 移入的盘点/看板/详情，盘点优先补缺口）：租赁循环（组装★/租赁单/退租/四态）+ BOM + 丢损赔偿 + 应付简化 + 我的待办；2026-11-17 上线 | C24: =SUMIF('功能点评估（全栈）'!$G$4:$G$69,$A24,'功能点评估（全栈）'!$H$4:$H$69) -> 39 | D24: 2026-10-19 | E24: 2026-11-17
A25: V2.0 | B25: 深化版 · +8 页：租入三单（L3/L4）+ 路凯对接 + 财务收口（开票/水单核销★/项目损益）+ 日志字典；依赖未定项全部收在此版 | C25: =SUMIF('功能点评估（全栈）'!$G$4:$G$69,$A25,'功能点评估（全栈）'!$H$4:$H$69) -> 20 | D25: 2026-11-18 | E25: 2026-12-07
A26: 各版 | B26: 测试/数据迁移/上线部署（C1~C3，8 行）——每版上线前各跑一轮，按版重复投入 | C26: =SUMIF('功能点评估（全栈）'!$G$4:$G$69,$A26,'功能点评估（全栈）'!$H$4:$H$69) -> 45 | D26: 2026-10-08 | E26: 2026-12-18
B27: 版本合计（校验，应等于上方总合计） | C27: =SUM(C22:C26) -> 149 | D27: =IF(C27=C18,"✓ 一致","✗ 不一致") -> ✓ 一致
A29: 参数与折算
A30: 缓冲比例 | C30: 0.15 | D30: 黄格待填：建议 15%~20%，覆盖联调与管理裕度
A31: 投入人数 | C31: 3 | D31: 黄格待填：对应 P1-R01 第八节 #9
A32: 每月工作日 | C32: 21 | D32: 人月折算基准
A33: 含缓冲合计（人日） | C33: =C18*(1+C30) -> 171.35 | D33: 自动：合计×(1+缓冲)
A34: 日历工期（月） | C34: =C33/(C32*C31) -> 2.7198413 | D34: 自动：含缓冲÷(每月工作日×人数)
A35: 日历工期（周） | C35: =ROUND(C34*4.33,1) -> 11.8 | D35: 自动

Sheet 功能点评估（全栈）
A1: P1-R03 工期评估表 · 功能点级（全栈口径）
A2: 口径：人日含概要设计+编码+自测；每功能点一行、不分前后端（类型=全栈）。2026-09-05 按方案二（买卖先行）标定「版本」列：V1.0 买卖版 21 页 / V1.1 租赁版 +16 页 / V2.0 深化版 +8 页，前置=调研+底座、各版=测试迁移上线每版重复投入。标（待补）的 10 行为原型已有但 §5.1 未编 FP 码的页面。人日/评估人/开始/结束全部留白，由道远与开发逐行填写；上一版估算归档于 99-归档/P1-R03-工期评估表-20260905.xlsx。｜2026-09-06 更新：按 3 名全栈开发、2026-09-07~09-10 芋道（yudao）JDK21 底座搭建、09-10 起业务开发、原型基本确定（前置压缩）口径填入人日初评；「各版」行 H=单轮人日×3 版；评估人/起止列留白待道远与开发复核微调。｜2026-09-06 二次调整：为赶 V1.0 于 2026-10-30 上线，盘点单（FP3-05）/项目看板（FP2-03）/项目详情（FP2-04）共 8.5 人日移至 V1.1——V1.0 缩为 17 页、V1.1 扩为 +20 页，总人日不变。｜2026-09-06 方案 2.0：3 名全栈全部借助 Claude Code vibe coding，按净提速口径重估——列表/弹窗/文档类×0.6、录单+过账×0.7、复杂业务逻辑（库存过账/组装拆卸/计费/核销/路凯对接）×0.75~0.85（人工设计主导）、调研评审不提速；整体 212→149 人日（-29.6%），15% 缓冲与版本范围不变。｜I 列「含缓冲人日」=H×(1+汇总!C30) 自动计算，与「按月版本规划」口径统一（171.35），汇报用 I 列。
A3: WBS | B3: 模块/阶段 | C3: 功能点 | D3: 任务 | E3: 类型 | F3: 对应原型页面 | G3: 版本 | H3: 人日 | I3: 含缓冲人日 （=人日×1.15） | J3: 评估人 | K3: 开始时间 | L3: 结束时间 | M3: 备注（风险/依赖）
A4: A1 | B4: 需求调研与PRD | C4: — | D4: 原型页面走查与字段确认（45 页逐页过、与吉客云/路凯现状对照） | E4: 调研 | F4: 45 页全量 | G4: 前置 | H4: 1.5 | I4: =H4*(1+汇总!$C$30) -> 1.725 | J4: 吕道远 | K4: 46272 | L4: 46273 | M4: 依赖 #2 #3：账号或全套截图；走查结论直接落到 PRD
A5: A1 | B5: 需求调研与PRD | C5: — | D5: 计费规则与单据流程确认（含四态计费口径） | E5: 调研 | F5: — | G5: 前置 | H5: 2 | I5: =H5*(1+汇总!$C$30) -> 2.3 | J5: 吕道远 | K5: 46274 | L5: 46275 | M5: 依赖 #1 #5：合同/报价单、单据样例
A6: A1 | B6: 需求调研与PRD | C6: — | D6: PRD 编写（按模块分册，以原型页面为底稿） | E6: 文档 | F6: 45 页全量 | G6: 前置 | H6: 1.5 | I6: =H6*(1+汇总!$C$30) -> 1.725 | J6: 吕道远 | K6: 46274 | L6: 46275
A7: A1 | B7: 需求调研与PRD | C7: — | D7: PRD 评审与范围冻结 | E7: 文档 | F7: 45 页全量 | G7: 前置 | H7: 1 | I7: =H7*(1+汇总!$C$30) -> 1.15 | J7: 吕道远 | K7: 46276 | L7: 46276 | M7: 客户确认后冻结范围，原型同步定稿
A8: A2 | B8: 原型设计 | C8: — | D8: 原型按评审反馈修订 | E8: 原型 | F8: 涉及页视反馈 | G8: 前置 | H8: 0.5 | I8: =H8*(1+汇总!$C$30) -> 0.575 | J8: 吕道远 | K8: 46275 | L8: 46275 | M8: v2.8 已交付（45 页 + 79 弹窗 + F01 导航图），仅评修订量，勿按全量重估
A9: A2 | B9: 原型设计 | C9: — | D9: 原型评审确认与定稿 | E9: 原型 | F9: 45 页全量 + F01 | G9: 前置 | H9: 0.5 | I9: =H9*(1+汇总!$C$30) -> 0.575 | J9: 吕道远 | K9: 46276 | L9: 46276 | M9: 与 PRD 冻结同节点收口
A10: B0 | B10: 公共技术底座 | C10: — | D10: 工程脚手架与 CI/CD | E10: 全栈 | F10: — | G10: 前置 | H10: 1.5 | I10: =H10*(1+汇总!$C$30) -> 1.725 | J10: 徐蔚 | K10: 46272 | L10: 46273 | M10: 本表新增项，非 P1-R01 功能点，评估时确认保留
A11: B0 | B11: 公共技术底座 | C11: — | D11: 登录认证与框架权限 | E11: 全栈 | F11: — | G11: 前置 | H11: 0.5 | I11: =H11*(1+汇总!$C$30) -> 0.575 | J11: 徐蔚 | K11: 46274 | L11: 46274 | M11: 原型未含登录页，按通用方案实现
A12: B0 | B12: 公共技术底座 | C12: — | D12: 通用组件（单据/列表/导入导出/弹窗/四段式详情） | E12: 全栈 | F12: 全站 | G12: 前置 | H12: 3.5 | I12: =H12*(1+汇总!$C$30) -> 4.025 | J12: 徐蔚 | K12: 46274 | L12: 46275 | M12: 复刻原型交互；79 个弹窗模板与四段式详情组件可直接参照
A13: B1 | B13: 基础数据 | C13: FP1-01 | D13: 项目档案：页面 + 表结构与接口 | E13: 全栈 | F13: 项目档案 | G13: V1.0 | H13: 1.5 | I13: =H13*(1+汇总!$C$30) -> 1.725 | J13: 徐蔚 | K13: 46275 | L13: 46276
A14: B1 | B14: 基础数据 | C14: FP1-02 | D14: 客商管理：三类客商档案（含开票资料） | E14: 全栈 | F14: 客商管理 | G14: V1.0 | H14: 2 | I14: =H14*(1+汇总!$C$30) -> 2.3 | J14: 徐蔚 | K14: 46279 | L14: 46280
A15: B1 | B15: 基础数据 | C15: FP1-03 | D15: 器具档案：页面 + 接口 | E15: 全栈 | F15: 器具档案 | G15: V1.0 | H15: 1 | I15: =H15*(1+汇总!$C$30) -> 1.15 | J15: 徐蔚 | K15: 46281 | L15: 46281
A16: B1 | B16: 基础数据 | C16: FP1-04 | D16: 零部件档案：页面 + 接口 | E16: 全栈 | F16: 零部件档案 | G16: V1.0 | H16: 1 | I16: =H16*(1+汇总!$C$30) -> 1.15 | J16: 徐蔚 | K16: 46282 | L16: 46282
A17: B1 | B17: 基础数据 | C17: FP1-05 | D17: 子母件 BOM：维护页 + 版本管理与配比校验 | E17: 全栈 | F17: BOM + BOM维护（2页） | G17: V1.1 | H17: 3 | I17: =H17*(1+汇总!$C$30) -> 3.45 | J17: 徐蔚 | K17: 46314 | L17: 46316 | M17: 配比错误需拦截；BOM 仅租赁域使用，随租赁版上线
A18: B1 | B18: 基础数据 | C18: FP1-06 | D18: 库位档案：页面 + 接口（仓/区/位三级） | E18: 全栈 | F18: 库位档案 | G18: V1.0 | H18: 1 | I18: =H18*(1+汇总!$C$30) -> 1.15 | J18: 徐蔚 | K18: 46283 | L18: 46283 | M18: 预留扫码接口（REQ-20）
A19: B2 | B19: 项目管理中心 | C19: FP2-01 | D19: 项目编码规则：规则引擎 + 配置 | E19: 全栈 | F19: 项目档案（编码规则弹窗） | G19: V1.0 | H19: 0.5 | I19: =H19*(1+汇总!$C$30) -> 0.575 | J19: 徐蔚 | K19: 46275 | L19: 46275
A20: B2 | B20: 项目管理中心 | C20: FP2-02 | D20: 上下游绑定：关系维护 + 模型接口 | E20: 全栈 | F20: 项目档案（上下游绑定弹窗） | G20: V1.0 | H20: 1 | I20: =H20*(1+汇总!$C$30) -> 1.15 | J20: 徐蔚 | K20: 46276 | L20: 46276
A21: B2 | B21: 项目管理中心 | C21: FP2-03 | D21: 项目看板：图表页 + 统计接口 | E21: 全栈 | F21: 首页·项目看板 | G21: V1.1 | H21: 1.5 | I21: =H21*(1+汇总!$C$30) -> 1.725 | J21: 徐蔚 | K21: 46290 | L21: 46293 | M21: V1.0→V1.1（2026-09-06 赶 10 月上线范围调整）
A22: B2 | B22: 项目管理中心 | C22: FP2-04 | D22: 明细查看：从汇总数据进入单据明细 | E22: 全栈 | F22: 项目详情 | G22: V1.1 | H22: 1.5 | I22: =H22*(1+汇总!$C$30) -> 1.725 | J22: 徐蔚 | K22: 46294 | L22: 46295 | M22: V1.0→V1.1（2026-09-06 赶 10 月上线范围调整）
A23: B2 | B23: 项目管理中心 | C23: （待补） | D23: 我的待办：18 类待办聚合入口 | E23: 全栈 | F23: 首页·我的待办 | G23: V1.1 | H23: 2 | I23: =H23*(1+汇总!$C$30) -> 2.3 | J23: 徐蔚 | K23: 46304 | L23: 46308 | M23: FP 码待补（§5.1 未编）；聚合各模块待办，单据类型齐了才有意义，随租赁版
A24: B3 | B24: 仓储作业 ★核心 | C24: FP3-01 | D24: 采购入库单（执行）：录单 + 入库过账与库存更新 | E24: 全栈 | F24: 采购入库 列表+录单（2页） | G24: V1.0 | H24: 2 | I24: =H24*(1+汇总!$C$30) -> 2.3 | J24: 徐蔚 | K24: 46276 | L24: 46279 | M24: V1.0 无采购订单时先手工入库（同吉客云现状），V1.0 内衔接 FP8-03 凭单发起
A25: B3 | B25: 仓储作业 ★核心 | C25: FP3-02 ★新增 | D25: 组装单：录单 + 库存转换引擎（A+B→C） | E25: 全栈 | F25: 组装 列表+录单（2页） | G25: V1.1 | H25: 4 | I25: =H25*(1+汇总!$C$30) -> 4.6 | J25: 徐蔚 | K25: 46314 | L25: 46318 | M25: 新逻辑：组装动作首次入系统；组装后散件转成品库存
A26: B3 | B26: 仓储作业 ★核心 | C26: FP3-03 | D26: 组合出库单：录单 + 出库过账与台账联动 | E26: 全栈 | F26: 组合出库 列表+录单（2页） | G26: V1.1 | H26: 2 | I26: =H26*(1+汇总!$C$30) -> 2.3 | J26: 徐蔚 | K26: 46321 | L26: 46322
A27: B3 | B27: 仓储作业 ★核心 | C27: FP3-04 | D27: 退租入库验收单：按零件核对缺损并记明细 | E27: 全栈 | F27: 退租入库列表（审核弹窗） | G27: V1.1 | H27: 2 | I27: =H27*(1+汇总!$C$30) -> 2.3 | J27: 徐蔚 | K27: 46323 | L27: 46324 | M27: 由退租申请（B4）触发；退租入库加拆散去向（v2.8）
A28: B3 | B28: 仓储作业 ★核心 | C28: FP3-05 | D28: 盘点单：零件/组合双口径 + 盘盈亏过账 | E28: 全栈 | F28: 盘点 列表+录入（2页） | G28: V1.1 | H28: 3 | I28: =H28*(1+汇总!$C$30) -> 3.45 | J28: 徐蔚 | K28: 46309 | L28: 46311 | M28: V1.0→V1.1（2026-09-06 赶 10 月上线范围调整）
A29: B3 | B29: 仓储作业 ★核心 | C29: FP3-06 | D29: 库存查询：零件/组合双视角 + 库存流水 | E29: 全栈 | F29: 库存查询（含流水弹窗） | G29: V1.0 | H29: 2 | I29: =H29*(1+汇总!$C$30) -> 2.3 | J29: 徐蔚 | K29: 46280 | L29: 46281
A30: B3 | B30: 仓储作业 ★核心 | C30: （待补） | D30: 销售出库单：录单 + 出库过账（买卖线出库执行） | E30: 全栈 | F30: 销售出库列表（新建/审核弹窗） | G30: V1.0 | H30: 2 | I30: =H30*(1+汇总!$C$30) -> 2.3 | J30: 徐蔚 | K30: 46282 | L30: 46283 | M30: FP 码待补；买卖线核心出库单
A31: B3 | B31: 仓储作业 ★核心 | C31: （待补） | D31: 其他入库单：无单据来源杂项入库 | E31: 全栈 | F31: 其他入库列表（新建/审核弹窗） | G31: V1.0 | H31: 1.5 | I31: =H31*(1+汇总!$C$30) -> 1.725 | J31: 徐蔚 | K31: 46286 | L31: 46287 | M31: FP 码待补
A32: B3 | B32: 仓储作业 ★核心 | C32: （待补） | D32: 其他出库单：报废/杂项出库 | E32: 全栈 | F32: 其他出库列表（新建/审核弹窗） | G32: V1.0 | H32: 1.5 | I32: =H32*(1+汇总!$C$30) -> 1.725 | J32: 徐蔚 | K32: 46288 | L32: 46289 | M32: FP 码待补
A33: B3 | B33: 仓储作业 ★核心 | C33: （待补） | D33: 库存调拨单：库间调拨 + 过账 | E33: 全栈 | F33: 库存调拨列表（新建/审核弹窗） | G33: V1.0 | H33: 1.5 | I33: =H33*(1+汇总!$C$30) -> 1.725 | J33: 徐蔚 | K33: 46290 | L33: 46293 | M33: FP 码待补
A34: B3 | B34: 仓储作业 ★核心 | C34: （待补） | D34: 拆卸单：C→A+B 逆向、散件回库 | E34: 全栈 | F34: 拆卸管理列表（新建/审核弹窗） | G34: V1.1 | H34: 3 | I34: =H34*(1+汇总!$C$30) -> 3.45 | J34: 徐蔚 | K34: 46325 | L34: 46329 | M34: FP 码待补；组装逆向，应对日计划变更
A35: B3 | B35: 仓储作业 ★核心 | C35: （待补） | D35: 租入入库单：租入包装验收入库（L3/L4） | E35: 全栈 | F35: 租入入库列表（确认弹窗） | G35: V2.0 | H35: 1.5 | I35: =H35*(1+汇总!$C$30) -> 1.725 | J35: 徐蔚 | K35: 46337 | L35: 46338 | M35: FP 码待补；租入体系独立单据（09-04 拍板）
A36: B3 | B36: 仓储作业 ★核心 | C36: （待补） | D36: 租入归还单：归还供应商出库（L3/L4） | E36: 全栈 | F36: 租入归还列表（新建/审核弹窗） | G36: V2.0 | H36: 1.5 | I36: =H36*(1+汇总!$C$30) -> 1.725 | J36: 徐蔚 | K36: 46339 | L36: 46342 | M36: FP 码待补
A37: B4 | B37: 包装管理（租赁） | C37: FP4-01 | D37: 租出台账：页面 + 接口 | E37: 全栈 | F37: 租出台账 | G37: V1.1 | H37: 1.5 | I37: =H37*(1+汇总!$C$30) -> 1.725 | J37: 徐蔚 | K37: 46317 | L37: 46318 | M37: 资产来源标记（v2.8）
A38: B4 | B38: 包装管理（租赁） | C38: FP4-02 | D38: 在租台账：在库/在途/客户端/退租四态统计 | E38: 全栈 | F38: 在租台账（器具出租履历弹窗） | G38: V1.1 | H38: 3 | I38: =H38*(1+汇总!$C$30) -> 3.45 | J38: 徐蔚 | K38: 46321 | L38: 46323
A39: B4 | B39: 包装管理（租赁） | C39: FP4-03 | D39: 循环状态与计费：状态流转 + 按数量结算 | E39: 全栈 | F39: 在租台账（状态操作） | G39: V1.1 | H39: 3 | I39: =H39*(1+汇总!$C$30) -> 3.45 | J39: 徐蔚 | K39: 46307 | L39: 46310 | M39: #1 计费规则未确认；租金自动计费（US-14）暂不在基线
A40: B4 | B40: 包装管理（租赁） | C40: FP4-04 | D40: 丢损赔偿单：退租缺损自动生成赔偿应收 | E40: 全栈 | F40: 丢损赔偿单（审核/报废弹窗） | G40: V1.1 | H40: 2 | I40: =H40*(1+汇总!$C$30) -> 2.3 | J40: 徐蔚 | K40: 46330 | L40: 46331 | M40: 按对象转单据：客户→应收 / 运营方·供应商→应付（道远 09-04 拍板）
A41: B4 | B41: 包装管理（租赁） | C41: FP4-05 | D41: 租赁单（出租）：向客户租出、生成租赁单 | E41: 全栈 | F41: 租赁单列表（新建/审核弹窗） | G41: V1.1 | H41: 2 | I41: =H41*(1+汇总!$C$30) -> 2.3 | J41: 徐蔚 | K41: 46324 | L41: 46325 | M41: 替代原「客户下单」，关联项目与客户
A42: B4 | B42: 包装管理（租赁） | C42: （待补） | D42: 退租申请：客户退租入口，触发验收 | E42: 全栈 | F42: 退租申请列表（新建/审核弹窗） | G42: V1.1 | H42: 2 | I42: =H42*(1+汇总!$C$30) -> 2.3 | J42: 徐蔚 | K42: 46328 | L42: 46329 | M42: FP 码待补；L4 退租申请节点（v2.8）
A43: B5 | B43: 订单管理 | C43: FP5-01 | D43: 订单管理（代下单）：项目经理代客户下单、统一订单列表 | E43: 全栈 | F43: 销售订单列表（租赁/买卖两用） | G43: V1.0 | H43: 2 | I43: =H43*(1+汇总!$C$30) -> 2.3 | J43: 徐蔚 | K43: 46276 | L43: 46279 | M43: REQ-07：客户发 PO、不再分客户端；V1.0 先跑买卖线订单
A44: B5 | B44: 订单管理 | C44: FP5-02 | D44: 订单审核：工作台 + 审核流转 | E44: 全栈 | F44: 销售订单审核弹窗 | G44: V1.0 | H44: 1 | I44: =H44*(1+汇总!$C$30) -> 1.15 | J44: 徐蔚 | K44: 46281 | L44: 46281
A45: B5 | B45: 订单管理 | C45: FP5-03 | D45: 订单同步（路凯）：同步通道 + 记录重发 | E45: 全栈 | F45: 后台通道（无独立页） | G45: V2.0 | H45: 4 | I45: =H45*(1+汇总!$C$30) -> 4.6 | J45: 徐蔚 | K45: 46337 | L45: 46343 | M45: #6 对接方式待定，评估按导出/接口两档
A46: B5 | B46: 订单管理 | C46: FP5-04 | D46: 结算数据导出：数据生成 + 传递 | E46: 全栈 | F46: 后台逻辑 + 导出入口 | G46: V2.0 | H46: 2 | I46: =H46*(1+汇总!$C$30) -> 2.3 | J46: 徐蔚 | K46: 46335 | L46: 46336 | M46: #6 结算格式待路凯方提供
A47: B6 | B47: 财务协同 | C47: FP6-01 | D47: 应收账单生成：归集规则 + 账单页 | E47: 全栈 | F47: 应收账单（生成/详情弹窗） | G47: V1.0 | H47: 2.5 | I47: =H47*(1+汇总!$C$30) -> 2.875 | J47: 徐蔚 | K47: 46282 | L47: 46286
A48: B6 | B48: 财务协同 | C48: FP6-02 | D48: 开票登记与发票上传：登记 + 应收关联 | E48: 全栈 | F48: 开票登记（新建/详情弹窗） | G48: V2.0 | H48: 1.5 | I48: =H48*(1+汇总!$C$30) -> 1.725 | J48: 徐蔚 | K48: 46337 | L48: 46338 | M48: 依赖 #8 开票主体信息
A49: B6 | B49: 财务协同 | C49: FP6-03 | D49: 回款登记：到账录入 + 关联 | E49: 全栈 | F49: 回款登记（收款登记弹窗） | G49: V1.0 | H49: 1.5 | I49: =H49*(1+汇总!$C$30) -> 1.725 | J49: 徐蔚 | K49: 46287 | L49: 46288
A50: B6 | B50: 财务协同 | C50: FP6-04 ★补缺 | D50: 银行水单核销：导入勾对 + 部分核销 + 对账联调 | E50: 全栈 | F50: 银行水单核销（勾对工作台） | G50: V2.0 | H50: 4 | I50: =H50*(1+汇总!$C$30) -> 4.6 | J50: 徐蔚 | K50: 46343 | L50: 46349 | M50: 现状缺失环节；依赖 #5 水单样例
A51: B6 | B51: 财务协同 | C51: FP6-05 | D51: 项目盈亏报表：汇总计算 + 报表页 | E51: 全栈 | F51: 盈亏报表 | G51: V2.0 | H51: 2.5 | I51: =H51*(1+汇总!$C$30) -> 2.875 | J51: 徐蔚 | K51: 46343 | L51: 46345 | M51: 须应收应付数据齐后才准
A52: B6 | B52: 财务协同 | C52: FP6-06 ★新增 | D52: 应付账单：采购/租入自动生成应付（第一期简化） | E52: 全栈 | F52: 应付账单（新建/详情弹窗） | G52: V1.1 | H52: 2 | I52: =H52*(1+汇总!$C$30) -> 2.3 | J52: 徐蔚 | K52: 46282 | L52: 46287 | M52: REQ-21；V1.1 简化版（登记+记录），完整核销流 V2.0
A53: B6 | B53: 财务协同 | C53: FP6-07 ★新增 | D53: 付款登记：银行付款录入，关联应付 | E53: 全栈 | F53: 付款登记（新建/付款确认弹窗） | G53: V1.1 | H53: 1.5 | I53: =H53*(1+汇总!$C$30) -> 1.725 | J53: 徐蔚 | K53: 46288 | L53: 46289 | M53: REQ-21
A54: B7 | B54: 系统管理 | C54: FP7-01 | D54: 组织与权限：用户/角色/数据权限（我方/客户区分） | E54: 全栈 | F54: 用户权限（角色管理弹窗） | G54: V1.0 | H54: 1 | I54: =H54*(1+汇总!$C$30) -> 1.15 | J54: 徐蔚 | K54: 46289 | L54: 46289
A55: B7 | B55: 系统管理 | C55: FP7-02 | D55: 操作日志：埋点存储 + 查询页 | E55: 全栈 | F55: 操作日志 | G55: V2.0 | H55: 0.5 | I55: =H55*(1+汇总!$C$30) -> 0.575 | J55: 徐蔚 | K55: 46339 | L55: 46339
A56: B7 | B56: 系统管理 | C56: FP7-03 | D56: 数据字典：字典管理 + 配置页 | E56: 全栈 | F56: 数据字典（新增字典项弹窗） | G56: V2.0 | H56: 0.5 | I56: =H56*(1+汇总!$C$30) -> 0.575 | J56: 徐蔚 | K56: 46342 | L56: 46342
A57: B8 | B57: 采购管理 | C57: FP8-01 | D57: 采购订单：新建 + 列表（先销后采/先采后销） | E57: 全栈 | F57: 采购订单列表（新建/详情弹窗） | G57: V1.0 | H57: 2 | I57: =H57*(1+汇总!$C$30) -> 2.3 | J57: 徐蔚 | K57: 46286 | L57: 46287 | M57: B1 采购线（09-04 拍板，不以销定采）
A58: B8 | B58: 采购管理 | C58: FP8-02 | D58: 采购订单审核：状态流（待提交/待审核/已完成） | E58: 全栈 | F58: 采购订单审核弹窗 | G58: V1.0 | H58: 1 | I58: =H58*(1+汇总!$C$30) -> 1.15 | J58: 徐蔚 | K58: 46288 | L58: 46288
A59: B8 | B59: 采购管理 | C59: FP8-03 | D59: 采购入库（发起）：到货登记关联采购订单 | E59: 全栈 | F59: 采购入库列表（凭单验收注记） | G59: V1.0 | H59: 1.5 | I59: =H59*(1+汇总!$C$30) -> 1.725 | J59: 徐蔚 | K59: 46289 | L59: 46290 | M59: 执行由 FP3-01 承接
A60: B8 | B60: 采购管理 | C60: FP8-04 | D60: 销售订单（买卖线）：客户购买订单 | E60: 全栈 | F60: 销售订单列表（与 FP5-01 同页两线） | G60: V1.0 | H60: 1.5 | I60: =H60*(1+汇总!$C$30) -> 1.725 | J60: 徐蔚 | K60: 46293 | L60: 46294 | M60: 审核后走销售出库（B3·V1.0）
A61: B8 | B61: 采购管理 | C61: （待补） | D61: 租入单：向路凯/供应商租入包装（L3/L4） | E61: 全栈 | F61: 租入单列表（新建/审核弹窗） | G61: V2.0 | H61: 2 | I61: =H61*(1+汇总!$C$30) -> 2.3 | J61: 徐蔚 | K61: 46332 | L61: 46336 | M61: FP 码待补；租入体系起点，触发租入入库
A62: C1 | B62: 测试 | C62: — | D62: 集成测试用例编写与执行 | E62: 测试 | F62: F01 导航图 v2.8 | G62: 各版 | H62: 10 | I62: =H62*(1+汇总!$C$30) -> 11.5 | J62: 徐蔚 | K62: 46303 | L62: 46360 | M62: 覆盖 F01 五条主线（B1 销售/采购双线、L1~L4）+ S1~S7 支线 + 应收/应付财务通道；每版上线前各跑一轮
A63: C1 | B63: 测试 | C63: — | D63: UAT 支持与缺陷修复 | E63: 测试 | F63: — | G63: 各版 | H63: 7 | I63: =H63*(1+汇总!$C$30) -> 8.05 | J63: 徐蔚 | K63: 46309 | L63: 46360
A64: C2 | B64: 数据迁移 | C64: — | D64: 主数据整理与导入模板 | E64: 迁移 | F64: — | G64: 各版 | H64: 4 | I64: =H64*(1+汇总!$C$30) -> 4.6 | J64: 徐蔚 | K64: 46303 | L64: 46358 | M64: 依赖 #4 主数据清单；V1.0 前导客商/器具/零部件，V1.1 前导 BOM 与在租
A65: C2 | B65: 数据迁移 | C65: — | D65: 期初库存与在租数据迁移（含租入在途） | E65: 迁移 | F65: — | G65: 各版 | H65: 6 | I65: =H65*(1+汇总!$C$30) -> 6.9 | J65: 徐蔚 | K65: 46308 | L65: 46359 | M65: 依赖 #5 现有台账导出；买卖库存随 V1.0、在租四态随 V1.1、租入在途随 V2.0
A66: C2 | B66: 数据迁移 | C66: — | D66: 迁移核对与差异处理 | E66: 迁移 | F66: — | G66: 各版 | H66: 3 | I66: =H66*(1+汇总!$C$30) -> 3.45 | J66: 徐蔚 | K66: 46310 | L66: 46360
A67: C3 | B67: 上线部署 | C67: — | D67: 环境部署与发布 | E67: 部署 | F67: — | G67: 各版 | H67: 3 | I67: =H67*(1+汇总!$C$30) -> 3.45 | J67: 徐蔚 | K67: 46308 | L67: 46360 | M67: 三版各发布一次
A68: C3 | B68: 上线部署 | C68: — | D68: 上线切换与并行期支持 | E68: 部署 | F68: — | G68: 各版 | H68: 5 | I68: =H68*(1+汇总!$C$30) -> 5.75 | J68: 徐蔚 | K68: 46310 | L68: 46363
A69: C3 | B69: 上线部署 | C69: — | D69: 线上试运行与并行验证（真实订单并行跑、问题快速响应） | E69: 测试 | F69: — | G69: 各版 | H69: 7 | I69: =H69*(1+汇总!$C$30) -> 8.05 | J69: 徐蔚 | K69: 46311 | L69: 46374 | M69: 建议每版预留试运行窗口（V1.0 2~4 周、后续版 1~2 周），客户验收后转正式运行
D70: 合计（人日） | H70: =SUM(H4:H69) -> 149 | I70: =SUM(I4:I69) -> 171.35
A72: 颜色图例
B73: 表头（白字）
B74: WBS 编号列
B75: 版本 = V1.0 买卖版
B76: 版本 = V1.1 租赁版
B77: 版本 = V2.0 深化版
B78: 前置/各版 + 公式自动计算（勿手改）
B79: FP 码待补行（§5.1 未编）
B80: 风险条目（按月表 R1~R5）
B81: 待填（现仅汇总表缓冲/人数 2 格）

Sheet 按月版本规划
A1: 按月版本规划 · 方案 2.0（3 全栈 + Claude Code vibe coding · 2026-09-07 开工 · 含 15% 缓冲 · 2026 年内全量交付）
A2: 口径：计划人日=功能点表人日（AI 协作净口径）×1.15；产能=当月实际工作日×3 人（09 月自 09-07 起 18 天、10 月扣国庆 16 天、12 月 23 天）；AI 提速分档——列表/弹窗/文档×0.6、录单+过账×0.7、复杂逻辑×0.75~0.85、调研评审不提速，整体净提速约 30%（212→150 人日）；里程碑为目标值。
A3: 月份 | B3: 版本/阶段 | C3: 计划人日 （含缓冲） | D3: 当月产能 （人日） | E3: 负载率 | F3: 当月开发内容（功能点） | G3: 里程碑 / 上线节点
A4: 2026-09 | B4: 前置 + 底座 + V1.0 全量开发 | C4: 51.75 | D4: 54 | E4: 0.96 | F4: ① 09-07~09-09 芋道 JDK21 底座：Claude Code 搭建脚手架+CI/CD、登录认证适配，09-09~09-10 落编码规范与组件约定（三人三套 AI 风格靠这个统一）；② 并行：原型走查、计费规则确认、Claude 按原型 HTML 起草字段级 PRD（09-11 评审冻结）；③ 09-10 起 V1.0 全量：基础数据（客商/器具/零部件/库位）+ 项目域（档案/编码规则/上下游）+ 买卖链（采购/销售订单、出入库、库存查询/调拨、应收/回款、权限） | G4: 09-09 底座+规范就绪；09-11 PRD 冻结；09-30 V1.0 功能开发完成
A5: 2026-10 | B5: ★ V1.0 上线 + V1.1 主开发 | C5: 48 | D5: 48 | E5: 1 | F5: ① 10-08~10-15 轮1：集成测试（Claude 生成用例+自动化脚本）、UAT、主数据迁移（客商/器具/零部件）、部署、上线切换；② 10-16 ★ V1.0 买卖版上线；③ 10-19 起 V1.1 主开发：BOM 维护、组装单★、组合出库、退租申请+退租入库、拆卸单、租赁单、租出/在租台账四态（国庆仅 16 个工作日，本月满负荷） | G5: 10-15 轮1 测试退出；10-16 ★ V1.0 买卖版上线（17 页）；V1.0 试运行转正式
A6: 2026-11 | B6: ★ V1.1 上线 + V2.0 开发 + 轮3 启动 | C6: 63 | D6: 63 | E6: 1 | F6: ① V1.1 收尾（11-06 开发完成）：循环状态与计费、丢损赔偿、应付简化+付款、我的待办、移入 3 项（盘点优先补 V1.0 缺口、看板/详情）；② 11-09~11-16 轮2：集成测试+UAT、BOM 与在租数据迁移；③ 11-17 ★ V1.1 上线；④ 11-17~11-26 V2.0 开发：租入三单、路凯订单同步、结算导出、开票登记、水单核销、盈亏报表、日志字典；⑤ 11-27 轮3 启动 | G6: 11-06 V1.1 功能开发完成；11-17 ★ V1.1 租赁版上线（累计 37 页）；11-26 V2.0 开发完成
A7: 2026-12 | B7: ★ V2.0 上线 + 试运行 + 年内验收 | C7: 8.6 | D7: 69 | E7: 0.13 | F7: ① 12-01~12-04 轮3 收尾：集成测试、租入在途迁移、部署；② 12-07 ★ V2.0 深化版全量上线；③ 12-07~12-18 试运行（真实订单并行跑）+ 验收材料（12 月底前项目验收）；④ 富余产能启动 2027 增强 backlog：租金自动计费（US-14）、库位扫码（REQ-20）、资产轨迹物联网二期 | G7: 12-07 ★ V2.0 全量上线（45 页功能全量）；12-25 前后项目验收，2026 年内交付收口
A8: 合计 | C8: =SUM(C4:C7) -> 171.35 | D8: =SUM(D4:D7) -> 234 | E8: =C8/D8 -> 0.73226496 | F8: 全项目跨度 2026-09-07 ~ 2026-12-25（约 3.6 个月、80 个工作日；含缓冲总投入 171.35 人日（=149×1.15，与功能点表 I 列合计一致），较方案一 243.8 缩短 1.3 个月；12 月富余产能转 2027 增强 backlog）
A10: 版本里程碑一览（方案 2.0 vs 方案一）
A11: 版本 | B11: 上线/完成目标 | C11: 范围（对应功能点表「版本」列）
A12: 前置 | B12: 2026-09-07 ~ 09-11（方案一 09-16） | C12: 走查/计费确认/Claude 起草 PRD + 芋道底座（09-07~09-09 Claude 搭建，09-09~09-10 落规范）
A13: V1.0 买卖版 | B13: 2026-10-16 上线（方案一 10-30） | C13: 17 页：买卖全链 + 库存（查询/调拨/其他出入库）+ 应收/回款 + 权限
A14: V1.1 租赁版 | B14: 2026-11-17 上线（方案一 12-10） | C14: +20 页：盘点/看板/详情（移入）+ 租赁循环（组装★/租赁/退租/四态）+ BOM + 丢损 + 应付简化 + 待办
A15: V2.0 深化版 | B15: 2026-12-07 上线（方案一 01-15） | C15: +8 页：租入三单 + 路凯对接 + 财务收口（开票/水单核销★/盈亏）+ 日志字典
A16: 验收收口 | B16: 2026-12-25 前后（方案一 2027-01-31） | C16: 试运行 2 周 + 验收；12 月富余产能启动 US-14 租金计费 / REQ-20 扫码等 2027 backlog
A17: 各版（×3 轮） | B17: 10-08 / 11-09 / 12-01 启动 | C17: 测试/UAT/迁移/部署/切换/试运行——单轮 15 人日×3 版=45 人日（含缓冲 51.75）
A19: AI 协作（Claude Code）前提与风险
A20: R1 评审带宽 | B20: AI 产出量大，3 名工程师须固定每日代码评审节奏，否则质量债累积击穿 15% 缓冲
A21: R2 风格统一 | B21: 底座周内（09-09~09-10）必须落编码规范+组件约定+prompt 素材库（42 页原型 HTML+本表），避免三人三套 AI 风格
A22: R3 关键逻辑 | B22: 库存过账/组装拆卸/四态计费/水单核销以人工设计为主、AI 辅助实现——对应行提速仅按 75%~85% 计，勿再压
A23: R4 磨合回退 | B23: 若 AI 协作磨合不顺（净提速退化至 ×0.85），V2.0 顺延至 12 月中下旬，仍在 2026 年内；激进档（×0.6）可再提前约 1 周
A24: R5 外部依赖 | B24: 路凯对接方式（#6）、水单样例（#5）、开票主体（#8）、主数据清单（#4）须按新节点提前到位——10 月中旬前拿到主数据是 V1.0 上线硬前提
